[
  {
    "id": "9df87b6a-e850-4db9-961f-73a27039ed13",
    "data": [
      {
        "text": "Have you ever tried Doggy style sex",
        "userDefined": false
      }
    ],
    "isTemplate": false,
    "count": 0,
    "updated": 1514134930
  },
  {
    "id": "5ccf8c7d-602a-436d-9d76-3be9fc2b0f93",
    "data": [
      {
        "text": "Have you ever tried Hard Core?",
        "userDefined": false
      }
    ],
    "isTemplate": false,
    "count": 0,
    "updated": 1514134930
  },
  {
    "id": "6b83bff3-a9d4-428e-ac6c-675c3243e243",
    "data": [
      {
        "text": "Have you ever tried anal?",
        "userDefined": false
      }
    ],
    "isTemplate": false,
    "count": 0,
    "updated": 1514134930
  }
]