[
  {
    "id": "7b90ac23-bbc4-4eae-8d74-52a5598cd160",
    "data": [
      {
        "text": "you mother fuck",
        "userDefined": false
      }
    ],
    "isTemplate": false,
    "count": 0,
    "updated": 0
  },
  {
    "id": "fce2918a-dab2-4f28-85be-3ee496484530",
    "data": [
      {
        "text": "Your mother\u0027s pussy",
        "userDefined": false
      }
    ],
    "isTemplate": false,
    "count": 0
  },
  {
    "id": "97f9479f-5884-401a-89de-3276f0fee0b3",
    "data": [
      {
        "text": "May worms infest your ass-hole",
        "userDefined": false
      }
    ],
    "isTemplate": false,
    "count": 0
  },
  {
    "id": "57118210-ac97-4a29-9191-7d654527fe36",
    "data": [
      {
        "text": "Son of donkey",
        "userDefined": false
      }
    ],
    "isTemplate": false,
    "count": 0
  },
  {
    "id": "d546751d-0601-4a3a-a586-fe87a1977af0",
    "data": [
      {
        "text": "Whore",
        "userDefined": false
      }
    ],
    "isTemplate": false,
    "count": 0
  },
  {
    "id": "88a4588a-7f7a-4d56-ac55-a7144bdbb331",
    "data": [
      {
        "text": "You fucker",
        "userDefined": false
      }
    ],
    "isTemplate": false,
    "count": 0
  },
  {
    "id": "684d4a6b-76e2-429e-b4a0-c1a999842838",
    "data": [
      {
        "text": " Sister\u0027s dick",
        "userDefined": false
      }
    ],
    "isTemplate": false,
    "count": 0
  },
  {
    "id": "5560246a-8ea6-4d3f-8002-5a8d680d9505",
    "data": [
      {
        "text": "Vaginal uncle",
        "userDefined": false
      }
    ],
    "isTemplate": false,
    "count": 0
  },
  {
    "id": "7aefd780-72ea-4d01-9ed6-0040fbc691d4",
    "data": [
      {
        "text": "Lizard\u0027s cunt hairs",
        "userDefined": false
      }
    ],
    "isTemplate": false,
    "count": 0
  },
  {
    "id": "236c84fb-fad0-42cb-94bc-2ba8c6b83bf4",
    "data": [
      {
        "text": "Hair of vagina",
        "userDefined": false
      }
    ],
    "isTemplate": false,
    "count": 0
  },
  {
    "id": "e05b914c-e7f1-4d6a-8488-c9613b42816e",
    "data": [
      {
        "text": "Pussy whipped",
        "userDefined": false
      }
    ],
    "isTemplate": false,
    "count": 0
  },
  {
    "id": "05294d51-497a-4d41-acae-34e1423c56fc",
    "data": [
      {
        "text": "idiot\u0027s brain has gone to eat grass",
        "userDefined": false
      }
    ],
    "isTemplate": false,
    "count": 1
  },
  {
    "id": "be64fcce-748e-41ea-8b2b-c52f5c8383b6",
    "data": [
      {
        "text": "Pussy lid",
        "userDefined": false
      }
    ],
    "isTemplate": false,
    "count": 0
  },
  {
    "id": "8c100a7b-4c95-4c36-b045-a5324bf0efa7",
    "data": [
      {
        "text": "Snack fried in pussy sweat",
        "userDefined": false
      }
    ],
    "isTemplate": false,
    "count": 0
  },
  {
    "id": "9f2b1539-468c-4e78-a823-66060afa43cc",
    "data": [
      {
        "text": "bastard",
        "userDefined": false
      }
    ],
    "isTemplate": false,
    "count": 0
  },
  {
    "id": "24394225-0bbf-4017-bebf-a50560479c70",
    "data": [
      {
        "text": "Shit",
        "userDefined": false
      }
    ],
    "isTemplate": false,
    "count": 0
  },
  {
    "id": "211dcc23-893a-48e2-986d-49069602a9de",
    "data": [
      {
        "text": "Bloody bitch",
        "userDefined": false
      }
    ],
    "isTemplate": false,
    "count": 0
  },
  {
    "id": "c068fee4-acea-4616-b558-2dd90fa9306e",
    "data": [
      {
        "text": "Bloody dog",
        "userDefined": false
      }
    ],
    "isTemplate": false,
    "count": 0
  },
  {
    "id": "0b27a8d9-d71c-4493-840e-027c99278801",
    "data": [
      {
        "text": "HOOKER",
        "userDefined": false
      }
    ],
    "isTemplate": false,
    "count": 0
  },
  {
    "id": "c53dca43-c94e-47c9-8cf5-7c46e5d115e1",
    "data": [
      {
        "text": "FART",
        "userDefined": false
      }
    ],
    "isTemplate": false,
    "count": 0
  },
  {
    "id": "3e85254c-ce4b-485f-9deb-2b646e2858ba",
    "data": [
      {
        "text": "Bitch",
        "userDefined": false
      }
    ],
    "isTemplate": false,
    "count": 0
  },
  {
    "id": "23a1d85d-613e-42ad-a4aa-36c470911535",
    "data": [
      {
        "text": "Penis, dick, cock",
        "userDefined": false
      }
    ],
    "isTemplate": false,
    "count": 0
  },
  {
    "id": "ac464931-2247-4193-acd2-13a0ebcd701f",
    "data": [
      {
        "text": "Idiot",
        "userDefined": false
      }
    ],
    "isTemplate": false,
    "count": 0
  },
  {
    "id": "5344a6ab-ef98-4b88-89f0-8fa0e66bae10",
    "data": [
      {
        "text": "Asshole",
        "userDefined": false
      }
    ],
    "isTemplate": false,
    "count": 0
  },
  {
    "id": "31bc2435-6791-4b39-8ea7-f3a237da9ffa",
    "data": [
      {
        "text": "ASS",
        "userDefined": false
      }
    ],
    "isTemplate": false,
    "count": 1
  },
  {
    "id": "81c7372a-35d3-4394-9a8e-dbed05a038d9",
    "data": [
      {
        "text": "Fucker",
        "userDefined": false
      }
    ],
    "isTemplate": false,
    "count": 0
  },
  {
    "id": "f628d84c-10d8-4d74-b57e-831e63345261",
    "data": [
      {
        "text": "Fucker",
        "userDefined": false
      }
    ],
    "isTemplate": false,
    "count": 0
  },
  {
    "id": "736d25dd-eecf-4d9a-a953-51919d196193",
    "data": [
      {
        "text": "Pimp",
        "userDefined": false
      }
    ],
    "isTemplate": false,
    "count": 0
  },
  {
    "id": "40d9c303-2bca-4fac-acfc-120ddb99efb3",
    "data": [
      {
        "text": "Daughter fucker",
        "userDefined": false
      }
    ],
    "isTemplate": false,
    "count": 0
  },
  {
    "id": "f1da8d10-4a36-44b7-9e75-cece641938a9",
    "data": [
      {
        "text": "Sister fucker",
        "userDefined": false
      }
    ],
    "isTemplate": false,
    "count": 0
  },
  {
    "id": "1c404b29-c92f-4ce8-9b9d-60998ca675da",
    "data": [
      {
        "text": "BORN FROM A ROTTEN PUSSY",
        "userDefined": false
      }
    ],
    "isTemplate": false,
    "count": 0
  },
  {
    "id": "f5a41798-da06-4640-84be-9f4ea7313ac1",
    "data": [
      {
        "text": "Fuck you",
        "userDefined": false
      }
    ],
    "isTemplate": false,
    "count": 0,
    "updated": 0
  },
  {
    "id": "265d77c2-530b-4b59-920b-4c1714ee10ba",
    "data": [
      {
        "text": "Press boobs",
        "userDefined": false
      }
    ],
    "isTemplate": false,
    "count": 0,
    "updated": 0
  },
  {
    "id": "c58bbde2-179d-4b62-a7bb-b1db09482062",
    "data": [
      {
        "text": "Fuck",
        "userDefined": false
      }
    ],
    "isTemplate": false,
    "count": 0,
    "updated": 0
  },
  {
    "id": "54374c80-e3f8-49e6-84a9-25ab1dc03bb5",
    "data": [
      {
        "text": "Mother fucker",
        "userDefined": false
      }
    ],
    "isTemplate": false,
    "count": 0,
    "updated": 0
  },
  {
    "id": "272d96d8-9769-4075-9569-5dbaea689d2a",
    "data": [
      {
        "text": "can i fuck you",
        "userDefined": false
      }
    ],
    "isTemplate": false,
    "count": 0,
    "updated": 1514212152
  },
  {
    "id": "1c32c57f-b09c-499a-b618-bbc45d4cd6a4",
    "data": [
      {
        "text": "I went to fuck you",
        "userDefined": false
      }
    ],
    "isTemplate": false,
    "count": 0,
    "updated": 1514212152
  },
  {
    "id": "dc89cc6c-4209-4caf-8dc5-7a0f1ffc45aa",
    "data": [
      {
        "text": "Fuck you",
        "userDefined": false
      }
    ],
    "isTemplate": false,
    "count": 0,
    "updated": 1514212152
  }
]