[
  {
    "id": "b330ce4c-4c51-4691-a855-ec176aada71f",
    "data": [
      {
        "text": "what do I look like",
        "userDefined": false
      }
    ],
    "isTemplate": false,
    "count": 0,
    "updated": 0
  },
  {
    "id": "242510fb-d64c-4bec-a866-857499a811dc",
    "data": [
      {
        "text": "how do I look",
        "userDefined": false
      }
    ],
    "isTemplate": false,
    "count": 0,
    "updated": 0
  },
  {
    "id": "328949a9-b46d-4ef3-ab59-4263fb01796a",
    "data": [
      {
        "text": "do you know what I look like",
        "userDefined": false
      }
    ],
    "isTemplate": false,
    "count": 0,
    "updated": 0
  },
  {
    "id": "43b6b9bd-a141-49b0-9cb1-612863558230",
    "data": [
      {
        "text": "can you see what I look like",
        "userDefined": false
      }
    ],
    "isTemplate": false,
    "count": 0,
    "updated": 0
  },
  {
    "id": "f7a8ed52-c27d-46fe-afab-ca12b15dceb6",
    "data": [
      {
        "text": "do I look good",
        "userDefined": false
      }
    ],
    "isTemplate": false,
    "count": 0,
    "updated": 0
  },
  {
    "id": "e4407b2c-8e31-4e1d-adf6-94af85e67e65",
    "data": [
      {
        "text": "what do you think I look like",
        "userDefined": false
      }
    ],
    "isTemplate": false,
    "count": 0,
    "updated": 0
  }
]