[
  {
    "id": "6c0b6f37-59a5-4b6a-b5e5-bdc4145fc9bf",
    "data": [
      {
        "text": "good",
        "meta": "@sys.ignore",
        "userDefined": true
      },
      {
        "text": " ",
        "userDefined": false
      },
      {
        "text": "good",
        "meta": "@sys.ignore",
        "userDefined": true
      },
      {
        "text": " ",
        "userDefined": false
      },
      {
        "text": "night",
        "meta": "@sys.ignore",
        "userDefined": true
      }
    ],
    "isTemplate": false,
    "count": 0,
    "updated": 0
  },
  {
    "id": "524846d7-b4c8-4954-848e-2bda7711b045",
    "data": [
      {
        "text": "have a ",
        "userDefined": false
      },
      {
        "text": "good",
        "meta": "@sys.ignore",
        "userDefined": true
      },
      {
        "text": " ",
        "userDefined": false
      },
      {
        "text": "night",
        "meta": "@sys.ignore",
        "userDefined": true
      }
    ],
    "isTemplate": false,
    "count": 1,
    "updated": 0
  },
  {
    "id": "341c66c4-5e43-4eb3-a008-48df6a0de6db",
    "data": [
      {
        "text": "thank you",
        "meta": "@sys.ignore",
        "userDefined": true
      },
      {
        "text": " good ",
        "userDefined": false
      },
      {
        "text": "night",
        "meta": "@sys.ignore",
        "userDefined": true
      }
    ],
    "isTemplate": false,
    "count": 0,
    "updated": 0
  },
  {
    "id": "78cc1b51-3d13-4f68-88cd-2ad83c4ec6ff",
    "data": [
      {
        "text": "thanks goodnight",
        "userDefined": false
      }
    ],
    "isTemplate": false,
    "count": 0,
    "updated": 0
  },
  {
    "id": "3c2bd975-e17e-43c4-9313-cd00d0a2aed5",
    "data": [
      {
        "text": "night",
        "meta": "@sys.ignore",
        "userDefined": false
      }
    ],
    "isTemplate": false,
    "count": 0,
    "updated": 0
  },
  {
    "id": "20bff1fb-a3d9-4dc1-9479-d32e24b3de98",
    "data": [
      {
        "text": "good",
        "meta": "@sys.ignore",
        "userDefined": false
      },
      {
        "text": " ",
        "userDefined": false
      },
      {
        "text": "night",
        "meta": "@sys.ignore",
        "userDefined": false
      },
      {
        "text": " see you ",
        "userDefined": false
      },
      {
        "text": "tomorrow",
        "meta": "@sys.ignore",
        "userDefined": false
      }
    ],
    "isTemplate": false,
    "count": 0,
    "updated": 0
  },
  {
    "id": "423e0ddd-e1d0-4f9e-b00a-2c2d358e35a7",
    "data": [
      {
        "text": "sweet dreams",
        "userDefined": false
      }
    ],
    "isTemplate": false,
    "count": 0,
    "updated": 0
  },
  {
    "id": "ae9521e9-30e8-4796-9f3a-9a1978e4c8f3",
    "data": [
      {
        "text": "good night for now",
        "userDefined": false
      }
    ],
    "isTemplate": false,
    "count": 0,
    "updated": 0
  },
  {
    "id": "26d23287-8059-4077-9e9b-a5e66b9ceee3",
    "data": [
      {
        "text": "night",
        "userDefined": false
      }
    ],
    "isTemplate": false,
    "count": 0,
    "updated": 0
  },
  {
    "id": "588dbbeb-d1b1-4d4e-a0a9-81c95b68512f",
    "data": [
      {
        "text": "good",
        "meta": "@sys.ignore",
        "userDefined": true
      },
      {
        "text": " ",
        "userDefined": false
      },
      {
        "text": "night",
        "meta": "@sys.ignore",
        "userDefined": true
      }
    ],
    "isTemplate": false,
    "count": 0,
    "updated": 0
  },
  {
    "id": "22c8f94e-fd9b-48e5-ab14-c95b9858be89",
    "data": [
      {
        "text": "okay have a good night",
        "userDefined": false
      }
    ],
    "isTemplate": false,
    "count": 0,
    "updated": 0
  },
  {
    "id": "35d096e0-c024-43b4-8997-248d81f4e584",
    "data": [
      {
        "text": "goodnight",
        "userDefined": false
      }
    ],
    "isTemplate": false,
    "count": 0,
    "updated": 0
  },
  {
    "id": "f6fb0093-510c-452c-93de-adefebcb401a",
    "data": [
      {
        "text": "bye ",
        "userDefined": false
      },
      {
        "text": "good",
        "meta": "@sys.ignore",
        "userDefined": true
      },
      {
        "text": " ",
        "userDefined": false
      },
      {
        "text": "night",
        "meta": "@sys.ignore",
        "userDefined": true
      }
    ],
    "isTemplate": false,
    "count": 0,
    "updated": 0
  },
  {
    "id": "fb42d4f6-b81a-4c65-a6eb-5f9dae806db5",
    "data": [
      {
        "text": " bye ",
        "userDefined": false
      },
      {
        "text": "good",
        "meta": "@sys.ignore",
        "userDefined": true
      },
      {
        "text": " ",
        "userDefined": false
      },
      {
        "text": "night",
        "meta": "@sys.ignore",
        "userDefined": true
      }
    ],
    "isTemplate": false,
    "count": 0,
    "updated": 0
  },
  {
    "id": "d9b4ccf1-22b9-4f17-9076-846f2fa34b83",
    "data": [
      {
        "text": "good",
        "meta": "@sys.ignore",
        "userDefined": true
      },
      {
        "text": " ",
        "userDefined": false
      },
      {
        "text": "night",
        "meta": "@sys.ignore",
        "userDefined": true
      },
      {
        "text": " to you",
        "userDefined": false
      }
    ],
    "isTemplate": false,
    "count": 0,
    "updated": 0
  },
  {
    "id": "4e33bc1a-e31c-42b7-b0c7-60c9fa7ab7cc",
    "data": [
      {
        "text": "good",
        "meta": "@sys.ignore",
        "userDefined": false
      },
      {
        "text": " ",
        "userDefined": false
      },
      {
        "text": "tonight",
        "meta": "@sys.ignore",
        "userDefined": false
      }
    ],
    "isTemplate": false,
    "count": 0,
    "updated": 0
  },
  {
    "id": "894dab82-d53b-4cb1-84fa-9507cc1ea2ad",
    "data": [
      {
        "text": "have a good night",
        "userDefined": false
      }
    ],
    "isTemplate": false,
    "count": 0,
    "updated": 0
  },
  {
    "id": "cb25441e-83e8-488e-adf0-da3efdb67462",
    "data": [
      {
        "text": "good",
        "meta": "@sys.ignore",
        "userDefined": true
      },
      {
        "text": " ",
        "userDefined": false
      },
      {
        "text": "night",
        "meta": "@sys.ignore",
        "userDefined": true
      },
      {
        "text": " bye",
        "userDefined": false
      }
    ],
    "isTemplate": false,
    "count": 0,
    "updated": 0
  },
  {
    "id": "f73ece8b-e70a-43c4-96bf-ac29f4ae38bf",
    "data": [
      {
        "text": "alright goodnight",
        "userDefined": false
      }
    ],
    "isTemplate": false,
    "count": 0,
    "updated": 0
  }
]