[
  {
    "id": "c2366596-6531-4f2d-9cf8-0acd92a1dd6c",
    "data": [
      {
        "text": "how ",
        "userDefined": false
      },
      {
        "text": "are",
        "meta": "@sys.ignore",
        "userDefined": false
      },
      {
        "text": " you",
        "userDefined": false
      }
    ],
    "isTemplate": false,
    "count": 1,
    "updated": 0
  },
  {
    "id": "d25aa842-96a5-4e56-97fe-9910fe5a178a",
    "data": [
      {
        "text": "how is ",
        "userDefined": false
      },
      {
        "text": "your",
        "meta": "@sys.ignore",
        "userDefined": false
      },
      {
        "text": " ",
        "userDefined": false
      },
      {
        "text": "evening",
        "meta": "@sys.ignore",
        "userDefined": false
      }
    ],
    "isTemplate": false,
    "count": 0,
    "updated": 0
  },
  {
    "id": "2a3105d8-0d5c-4491-98f9-971203f224b1",
    "data": [
      {
        "text": "how ",
        "userDefined": false
      },
      {
        "text": "are",
        "meta": "@sys.ignore",
        "userDefined": false
      },
      {
        "text": " you feeling",
        "userDefined": false
      }
    ],
    "isTemplate": false,
    "count": 0,
    "updated": 0
  },
  {
    "id": "a85923ea-b83a-4da7-95b6-3a28e114a4b5",
    "data": [
      {
        "text": "are you okay",
        "userDefined": false
      }
    ],
    "isTemplate": false,
    "count": 0,
    "updated": 0
  },
  {
    "id": "1071d1ab-75fa-4e94-ad5a-4f753f8d91d4",
    "data": [
      {
        "text": "is everything okay",
        "userDefined": false
      }
    ],
    "isTemplate": false,
    "count": 0,
    "updated": 0
  },
  {
    "id": "453271e7-efa9-4b0b-a9dc-52186fd03c61",
    "data": [
      {
        "text": "how do ",
        "userDefined": false
      },
      {
        "text": "you",
        "meta": "@sys.ignore",
        "userDefined": false
      },
      {
        "text": " do",
        "userDefined": false
      }
    ],
    "isTemplate": false,
    "count": 0,
    "updated": 0
  },
  {
    "id": "ae651963-201e-4042-9309-1e275622f461",
    "data": [
      {
        "text": "how is ",
        "userDefined": false
      },
      {
        "text": "it",
        "meta": "@sys.ignore",
        "userDefined": false
      }
    ],
    "isTemplate": false,
    "count": 0,
    "updated": 0
  },
  {
    "id": "b8d30806-02c0-47ef-9384-9956bb564a36",
    "data": [
      {
        "text": "how do you ",
        "userDefined": false
      },
      {
        "text": "feel",
        "meta": "@sys.ignore",
        "userDefined": false
      }
    ],
    "isTemplate": false,
    "count": 0,
    "updated": 0
  },
  {
    "id": "5a5287d0-ce77-4409-bd36-353828b1c283",
    "data": [
      {
        "text": "how ",
        "userDefined": false
      },
      {
        "text": "your",
        "meta": "@sys.ignore",
        "userDefined": false
      },
      {
        "text": " ",
        "userDefined": false
      },
      {
        "text": "day",
        "meta": "@sys.ignore",
        "userDefined": false
      },
      {
        "text": " is going",
        "userDefined": false
      }
    ],
    "isTemplate": false,
    "count": 0,
    "updated": 0
  },
  {
    "id": "8cbcba2e-a092-48e7-bf22-64f4f5daf427",
    "data": [
      {
        "text": "how is ",
        "userDefined": false
      },
      {
        "text": "it",
        "meta": "@sys.ignore",
        "userDefined": false
      },
      {
        "text": " going",
        "userDefined": false
      }
    ],
    "isTemplate": false,
    "count": 0,
    "updated": 0
  },
  {
    "id": "5841a620-bb9b-44f2-ae68-86d14177bcbc",
    "data": [
      {
        "text": "how about you",
        "userDefined": false
      }
    ],
    "isTemplate": false,
    "count": 0,
    "updated": 0
  },
  {
    "id": "29d336e2-4847-47ca-aefa-8180628c1936",
    "data": [
      {
        "text": "how ",
        "userDefined": false
      },
      {
        "text": "are",
        "meta": "@sys.ignore",
        "userDefined": false
      },
      {
        "text": " you going",
        "userDefined": false
      }
    ],
    "isTemplate": false,
    "count": 0,
    "updated": 0
  },
  {
    "id": "04eec293-da72-4ba7-b4c0-571c31f0d577",
    "data": [
      {
        "text": "how is ",
        "userDefined": false
      },
      {
        "text": "your",
        "meta": "@sys.ignore",
        "userDefined": false
      },
      {
        "text": " ",
        "userDefined": false
      },
      {
        "text": "day",
        "meta": "@sys.ignore",
        "userDefined": false
      }
    ],
    "isTemplate": false,
    "count": 0,
    "updated": 0
  },
  {
    "id": "dbce0a04-77d6-4842-bfca-a4e2ad8f72a6",
    "data": [
      {
        "text": "hope",
        "meta": "@sys.ignore",
        "userDefined": false
      },
      {
        "text": " you re having a pleasant ",
        "userDefined": false
      },
      {
        "text": "evening",
        "meta": "@sys.ignore",
        "userDefined": false
      }
    ],
    "isTemplate": false,
    "count": 0,
    "updated": 0
  },
  {
    "id": "10532c2c-471e-4ad5-80af-29a00d4ce149",
    "data": [
      {
        "text": "how has ",
        "userDefined": false
      },
      {
        "text": "your",
        "meta": "@sys.ignore",
        "userDefined": false
      },
      {
        "text": " ",
        "userDefined": false
      },
      {
        "text": "day",
        "meta": "@sys.ignore",
        "userDefined": false
      },
      {
        "text": " been",
        "userDefined": false
      }
    ],
    "isTemplate": false,
    "count": 0,
    "updated": 0
  },
  {
    "id": "63f49b11-4633-4e38-84bb-3424ace5974d",
    "data": [
      {
        "text": "how ",
        "userDefined": false
      },
      {
        "text": "are",
        "meta": "@sys.ignore",
        "userDefined": false
      },
      {
        "text": " the things going",
        "userDefined": false
      }
    ],
    "isTemplate": false,
    "count": 0,
    "updated": 0
  },
  {
    "id": "36c0af00-1f45-4418-bf7f-1be5c4594d69",
    "data": [
      {
        "text": "how ",
        "userDefined": false
      },
      {
        "text": "are",
        "meta": "@sys.ignore",
        "userDefined": false
      },
      {
        "text": " you ",
        "userDefined": false
      },
      {
        "text": "today",
        "meta": "@sys.ignore",
        "userDefined": false
      }
    ],
    "isTemplate": false,
    "count": 0,
    "updated": 0
  },
  {
    "id": "8cfe7bf4-fb78-4ff2-9617-7304e462f1c4",
    "data": [
      {
        "text": "how is your day going",
        "userDefined": false
      }
    ],
    "isTemplate": false,
    "count": 0,
    "updated": 0
  },
  {
    "id": "edca1731-8e95-4eaa-af89-3a6d86b9938a",
    "data": [
      {
        "text": "are",
        "meta": "@sys.ignore",
        "userDefined": false
      },
      {
        "text": " you having a ",
        "userDefined": false
      },
      {
        "text": "good",
        "meta": "@sys.ignore",
        "userDefined": false
      },
      {
        "text": " ",
        "userDefined": false
      },
      {
        "text": "day",
        "meta": "@sys.ignore",
        "userDefined": false
      }
    ],
    "isTemplate": false,
    "count": 0,
    "updated": 0
  },
  {
    "id": "3de5af9c-6851-4bee-a93e-0cf274798dbc",
    "data": [
      {
        "text": "how is ",
        "userDefined": false
      },
      {
        "text": "your",
        "meta": "@sys.ignore",
        "userDefined": false
      },
      {
        "text": " ",
        "userDefined": false
      },
      {
        "text": "day",
        "meta": "@sys.ignore",
        "userDefined": false
      },
      {
        "text": " going",
        "userDefined": false
      }
    ],
    "isTemplate": false,
    "count": 0,
    "updated": 0
  },
  {
    "id": "1c6ec8cc-efe8-4049-926a-8fc30bba01a5",
    "data": [
      {
        "text": "what about ",
        "userDefined": false
      },
      {
        "text": "your",
        "meta": "@sys.ignore",
        "userDefined": false
      },
      {
        "text": " ",
        "userDefined": false
      },
      {
        "text": "day",
        "meta": "@sys.ignore",
        "userDefined": false
      }
    ],
    "isTemplate": false,
    "count": 0,
    "updated": 0
  },
  {
    "id": "6e1756ea-0759-4eb8-9921-dd4b68c1e191",
    "data": [
      {
        "text": "how\u0027s your day",
        "userDefined": false
      }
    ],
    "isTemplate": false,
    "count": 0,
    "updated": 0
  },
  {
    "id": "51e9de70-46d1-44cc-b7bf-ddb32715b148",
    "data": [
      {
        "text": "I\u0027m",
        "meta": "@sys.ignore",
        "userDefined": false
      },
      {
        "text": " ",
        "userDefined": false
      },
      {
        "text": "fine",
        "meta": "@sys.ignore",
        "userDefined": false
      },
      {
        "text": " and you",
        "userDefined": false
      }
    ],
    "isTemplate": false,
    "count": 0,
    "updated": 0
  },
  {
    "id": "a95da19e-1ec5-496a-b425-3a7b5d25cb00",
    "data": [
      {
        "text": "what was ",
        "userDefined": false
      },
      {
        "text": "your",
        "meta": "@sys.ignore",
        "userDefined": false
      },
      {
        "text": " ",
        "userDefined": false
      },
      {
        "text": "day",
        "meta": "@sys.ignore",
        "userDefined": false
      },
      {
        "text": " like",
        "userDefined": false
      }
    ],
    "isTemplate": false,
    "count": 0,
    "updated": 0
  },
  {
    "id": "a70fba9d-f5ef-4bde-b21a-733c3e28ea20",
    "data": [
      {
        "text": "how was ",
        "userDefined": false
      },
      {
        "text": "your",
        "meta": "@sys.ignore",
        "userDefined": false
      },
      {
        "text": " ",
        "userDefined": false
      },
      {
        "text": "day",
        "meta": "@sys.ignore",
        "userDefined": false
      }
    ],
    "isTemplate": false,
    "count": 0,
    "updated": 0
  },
  {
    "id": "33a88352-fc26-4d20-962d-37528d9fa2be",
    "data": [
      {
        "text": "how has ",
        "userDefined": false
      },
      {
        "text": "your",
        "meta": "@sys.ignore",
        "userDefined": false
      },
      {
        "text": " ",
        "userDefined": false
      },
      {
        "text": "day",
        "meta": "@sys.ignore",
        "userDefined": false
      },
      {
        "text": " been going",
        "userDefined": false
      }
    ],
    "isTemplate": false,
    "count": 0,
    "updated": 0
  },
  {
    "id": "0507ef1b-a9f8-4b65-a5d0-10716eb81a00",
    "data": [
      {
        "text": "how is ",
        "userDefined": false
      },
      {
        "text": "your",
        "meta": "@sys.ignore",
        "userDefined": false
      },
      {
        "text": " ",
        "userDefined": false
      },
      {
        "text": "day",
        "meta": "@sys.ignore",
        "userDefined": false
      },
      {
        "text": " going ",
        "userDefined": false
      },
      {
        "text": "on",
        "meta": "@sys.ignore",
        "userDefined": false
      }
    ],
    "isTemplate": false,
    "count": 1,
    "updated": 0
  },
  {
    "id": "abf2946d-9fe8-4590-a4fb-7da36b094dbd",
    "data": [
      {
        "text": "how is ",
        "userDefined": false
      },
      {
        "text": "your",
        "meta": "@sys.ignore",
        "userDefined": false
      },
      {
        "text": " life",
        "userDefined": false
      }
    ],
    "isTemplate": false,
    "count": 0,
    "updated": 0
  },
  {
    "id": "3d3dc9c2-cdd9-4929-a8b2-ab1f2b581800",
    "data": [
      {
        "text": "how have ",
        "userDefined": false
      },
      {
        "text": "you",
        "meta": "@sys.ignore",
        "userDefined": false
      },
      {
        "text": " been",
        "userDefined": false
      }
    ],
    "isTemplate": false,
    "count": 0,
    "updated": 0
  },
  {
    "id": "c5914ed1-13fd-478a-a30f-c4dbe1d0c8e8",
    "data": [
      {
        "text": "how\u0027s your ",
        "userDefined": false
      },
      {
        "text": "day",
        "meta": "@sys.ignore",
        "userDefined": false
      },
      {
        "text": " going",
        "userDefined": false
      }
    ],
    "isTemplate": false,
    "count": 0,
    "updated": 0
  },
  {
    "id": "034b7ab0-5a40-4cdb-892b-75560dbb111b",
    "data": [
      {
        "text": "how are you doing this morning",
        "userDefined": false
      }
    ],
    "isTemplate": false,
    "count": 0,
    "updated": 0
  },
  {
    "id": "f6db9755-3a4c-47ff-b920-d65e2cfdb2a4",
    "data": [
      {
        "text": "are",
        "meta": "@sys.ignore",
        "userDefined": false
      },
      {
        "text": " you alright",
        "userDefined": false
      }
    ],
    "isTemplate": false,
    "count": 0,
    "updated": 0
  },
  {
    "id": "f38ac596-0aa7-4ccd-ba02-1025b9a17c49",
    "data": [
      {
        "text": "is everything ",
        "userDefined": false
      },
      {
        "text": "all",
        "meta": "@sys.ignore",
        "userDefined": false
      },
      {
        "text": " right",
        "userDefined": false
      }
    ],
    "isTemplate": false,
    "count": 0,
    "updated": 0
  },
  {
    "id": "06b79569-3977-401c-bc67-757843017147",
    "data": [
      {
        "text": "how are you getting on",
        "userDefined": false
      }
    ],
    "isTemplate": false,
    "count": 0,
    "updated": 0
  },
  {
    "id": "ce690256-5253-4648-928d-8ac5dac23438",
    "data": [
      {
        "text": "how is ",
        "userDefined": false
      },
      {
        "text": "your",
        "meta": "@sys.ignore",
        "userDefined": false
      },
      {
        "text": " ",
        "userDefined": false
      },
      {
        "text": "day",
        "meta": "@sys.ignore",
        "userDefined": false
      },
      {
        "text": " being",
        "userDefined": false
      }
    ],
    "isTemplate": false,
    "count": 0,
    "updated": 0
  },
  {
    "id": "b19a1aae-d6a1-4731-8172-936be8407b71",
    "data": [
      {
        "text": "how is ",
        "userDefined": false
      },
      {
        "text": "your",
        "meta": "@sys.ignore",
        "userDefined": false
      },
      {
        "text": " ",
        "userDefined": false
      },
      {
        "text": "morning",
        "meta": "@sys.ignore",
        "userDefined": false
      },
      {
        "text": " going",
        "userDefined": false
      }
    ],
    "isTemplate": false,
    "count": 0,
    "updated": 0
  },
  {
    "id": "a8b0c8e6-132e-4997-b054-4f14965ce775",
    "data": [
      {
        "text": "hope",
        "meta": "@sys.ignore",
        "userDefined": false
      },
      {
        "text": " ",
        "userDefined": false
      },
      {
        "text": "your",
        "meta": "@sys.ignore",
        "userDefined": false
      },
      {
        "text": " ",
        "userDefined": false
      },
      {
        "text": "day",
        "meta": "@sys.ignore",
        "userDefined": false
      },
      {
        "text": " is going ",
        "userDefined": false
      },
      {
        "text": "well",
        "meta": "@sys.ignore",
        "userDefined": false
      }
    ],
    "isTemplate": false,
    "count": 0,
    "updated": 0
  },
  {
    "id": "eb4c8479-abd6-44ca-9e5f-202e9fcef9a4",
    "data": [
      {
        "text": "how ",
        "userDefined": false
      },
      {
        "text": "are",
        "meta": "@sys.ignore",
        "userDefined": false
      },
      {
        "text": " you doing",
        "userDefined": false
      }
    ],
    "isTemplate": false,
    "count": 0,
    "updated": 0
  },
  {
    "id": "2217a9d1-c76f-41c3-b2c0-d4e3c3544e4d",
    "data": [
      {
        "text": "how\u0027s life",
        "userDefined": false
      }
    ],
    "isTemplate": false,
    "count": 0,
    "updated": 0
  },
  {
    "id": "d1e4cd94-d256-4079-879e-04c151ddd528",
    "data": [
      {
        "text": "how is ",
        "userDefined": false
      },
      {
        "text": "your",
        "meta": "@sys.ignore",
        "userDefined": false
      },
      {
        "text": " ",
        "userDefined": false
      },
      {
        "text": "morning",
        "meta": "@sys.ignore",
        "userDefined": false
      },
      {
        "text": " so far",
        "userDefined": false
      }
    ],
    "isTemplate": false,
    "count": 0,
    "updated": 0
  }
]