[
  {
    "id": "0e5e9ae0-3178-440e-b6af-4abbd624d0d1",
    "data": [
      {
        "text": "kya aap mere se hindi me baat kar sakte hai",
        "userDefined": false
      }
    ],
    "isTemplate": false,
    "count": 0,
    "updated": 1514104908
  },
  {
    "id": "f7dc5807-902f-40f9-b5fb-ca415306ae46",
    "data": [
      {
        "text": "aap ka naam kya hai",
        "userDefined": false
      }
    ],
    "isTemplate": false,
    "count": 0,
    "updated": 1514104908
  },
  {
    "id": "9a919b44-e6f9-4fa8-a74f-adfc635a745e",
    "data": [
      {
        "text": "aap ko hindi aati hai",
        "userDefined": false
      }
    ],
    "isTemplate": false,
    "count": 0,
    "updated": 1514104908
  },
  {
    "id": "80bc729a-6489-4fa5-8d47-619a3882ca4c",
    "data": [
      {
        "text": "can you speak in hindi",
        "userDefined": false
      }
    ],
    "isTemplate": false,
    "count": 0,
    "updated": 1514104908
  },
  {
    "id": "5330acf5-c6b8-41c6-bbd7-00d1321de5f6",
    "data": [
      {
        "text": "do you know hindi",
        "userDefined": false
      }
    ],
    "isTemplate": false,
    "count": 0,
    "updated": 1514104908
  },
  {
    "id": "37c6d160-94d3-42b9-9b2e-14253171ee85",
    "data": [
      {
        "text": "are you know hindi",
        "userDefined": false
      }
    ],
    "isTemplate": false,
    "count": 0,
    "updated": 1514104908
  }
]